README.md
setup.py
reeco_ml_preprocessing/__init__.py
reeco_ml_preprocessing/base.py
reeco_ml_preprocessing/preprocess_pipeline.py
reeco_ml_preprocessing.egg-info/PKG-INFO
reeco_ml_preprocessing.egg-info/SOURCES.txt
reeco_ml_preprocessing.egg-info/dependency_links.txt
reeco_ml_preprocessing.egg-info/requires.txt
reeco_ml_preprocessing.egg-info/top_level.txt
reeco_ml_preprocessing/convert_data_type/__init__.py
reeco_ml_preprocessing/convert_data_type/pd_np_transform.py
reeco_ml_preprocessing/create_static_covariate/__init__.py
reeco_ml_preprocessing/create_static_covariate/lunar.py
reeco_ml_preprocessing/manipulate_data/__init__.py
reeco_ml_preprocessing/manipulate_data/slicing.py
reeco_ml_preprocessing/process_numerical/__init__.py
reeco_ml_preprocessing/process_numerical/standard_scaler.py
reeco_ml_preprocessing/time_series/__init__.py
reeco_ml_preprocessing/time_series/cleaner.py
reeco_ml_preprocessing/time_series/simple_imputer.py
reeco_ml_preprocessing/time_series/sliding_window.py
reeco_ml_preprocessing/time_series/ts_imputer.py