Metadata-Version: 2.1
Name: reeco-ml-preprocessing
Version: 0.1.5
Summary: Package for ML preprocessing
Home-page: https://gitlab.com/vn-reecotech/Ari/reeco-data-platform/preprocessor
Download-URL: https://gitlab.com/vn-reecotech/Ari/reeco-data-platform/preprocessor
Author: ARI Technology
Author-email: dung.ut@ari.com.vn
License: UNKNOWN
Platform: UNKNOWN
